examples/__init__.py
examples/anthropic_basic_usage.py
examples/openai_basic_usage.py
examples/specific_ai_basic_usage.py
specific_ai/__init__.py
specific_ai/anthropic/__init__.py
specific_ai/anthropic/anthropic.py
specific_ai/common/__init__.py
specific_ai/common/inference.py
specific_ai/common/lm_response_types.py
specific_ai/common/task_type.py
specific_ai/common/tracing.py
specific_ai/openai/__init__.py
specific_ai/openai/client.py
specific_ai/openai/specific_ai_chat.py
specific_ai/openai/specific_ai_completions.py
specific_ai/specific/__init__.py
specific_ai/specific/client.py
specific_ai-0.1.6.dist-info/METADATA
specific_ai-0.1.6.dist-info/WHEEL
specific_ai-0.1.6.dist-info/top_level.txt
specific_ai-0.1.6.dist-info/RECORD
