Metadata-Version: 2.4
Name: specific-ai
Version: 0.1.6
Summary: specific.ai python sdk
Home-page: https://specific.ai/
Author: specific.ai team
Author-email: support@specific.ai
Classifier: Programming Language :: Python :: 3
Classifier: Operating System :: OS Independent
Requires-Dist: requests
Requires-Dist: openai
Requires-Dist: pydantic
Requires-Dist: anthropic
Provides-Extra: dev
Requires-Dist: pytest; extra == "dev"
Requires-Dist: pandas; extra == "dev"
Dynamic: author
Dynamic: author-email
Dynamic: classifier
Dynamic: description
Dynamic: description-content-type
Dynamic: home-page
Dynamic: provides-extra
Dynamic: requires-dist
Dynamic: summary
